README.txt
setup.cfg
setup.py
pyogp/__init__.py
pyogp.apps.egg-info/PKG-INFO
pyogp.apps.egg-info/SOURCES.txt
pyogp.apps.egg-info/dependency_links.txt
pyogp.apps.egg-info/entry_points.txt
pyogp.apps.egg-info/namespace_packages.txt
pyogp.apps.egg-info/not-zip-safe
pyogp.apps.egg-info/requires.txt
pyogp.apps.egg-info/top_level.txt
pyogp/apps/__init__.py
pyogp/apps/examples/AIS_inventory_handling.py
pyogp/apps/examples/__init__.py
pyogp/apps/examples/agent_login.py
pyogp/apps/examples/agent_manager.py
pyogp/apps/examples/appearance_management.py
pyogp/apps/examples/chat_and_instant_messaging.py
pyogp/apps/examples/chat_interface.py
pyogp/apps/examples/fetch_offline_ims.py
pyogp/apps/examples/fetch_profile_info.py
pyogp/apps/examples/group_chat.py
pyogp/apps/examples/group_chat_test.py
pyogp/apps/examples/group_creation.py
pyogp/apps/examples/inventory_handling.py
pyogp/apps/examples/inventory_transfer.py
pyogp/apps/examples/inventory_transfer_specify_agent.py
pyogp/apps/examples/login.py
pyogp/apps/examples/map_item_requests.py
pyogp/apps/examples/multi_agents_subprocess.py
pyogp/apps/examples/multi_region_connect.py
pyogp/apps/examples/object_create_edit.py
pyogp/apps/examples/object_create_permissions.py
pyogp/apps/examples/object_create_rez_script.py
pyogp/apps/examples/object_create_upload_via_caps.py
pyogp/apps/examples/object_creation.py
pyogp/apps/examples/object_properties.py
pyogp/apps/examples/object_tracking.py
pyogp/apps/examples/parcel_management.py
pyogp/apps/examples/parse_packets.py
pyogp/apps/examples/region_connect.py
pyogp/apps/examples/smoke_test.py
pyogp/apps/examples/voice_info.py
pyogp/apps/proxy/__init__.py
pyogp/apps/proxy/client_proxy.py
pyogp/apps/proxy/lib/__init__.py
pyogp/apps/proxy/lib/caps_proxy.py
pyogp/apps/proxy/lib/udpproxy.py
pyogp/apps/web/__init__.py
pyogp/apps/web/django/__init__.py
pyogp/apps/web/django/pyogp_webbot/__init__.py
pyogp/apps/web/django/pyogp_webbot/manage.py
pyogp/apps/web/django/pyogp_webbot/settings.py
pyogp/apps/web/django/pyogp_webbot/urls.py
pyogp/apps/web/django/pyogp_webbot/login/__init__.py
pyogp/apps/web/django/pyogp_webbot/login/models.py
pyogp/apps/web/django/pyogp_webbot/login/tests.py
pyogp/apps/web/django/pyogp_webbot/login/views.py